{
    "type": "Grand Prix",
    "coverage": "https://magic.wizards.com/en/events/coverage/gpric06",
    "date": "February 4-5, 2006",
    "season": "2006",
    "formats": [
        "Sealed Deck",
        "Booster Draft"
    ],
    "medium": "Tabletop",
    "id": "grand-prix-richmond-2006",
    "location": "Richmond, Virginia, United States",
    "logo": "gplogo",
    "name": "Grand Prix Richmond 2006",
    "standings": [
        {
            "money": 2400,
            "name": "Richard Hoaen",
            "propoints": 6
        },
        {
            "money": 1700,
            "name": "Jonathan Sonne",
            "propoints": 5
        },
        {
            "money": 1200,
            "name": "Adam Chambers",
            "propoints": 4
        },
        {
            "money": 1000,
            "name": "John Fiorillo",
            "propoints": 4
        },
        {
            "money": 800,
            "name": "Eugene Harvey",
            "propoints": 3
        },
        {
            "money": 800,
            "name": "Taylor Webb",
            "propoints": 3
        },
        {
            "money": 800,
            "name": "Gerry Thompson",
            "propoints": 3
        },
        {
            "money": 800,
            "name": "Michael Pinnegar",
            "propoints": 3
        },
        {
            "money": 500,
            "name": "Gadiel Szleifer",
            "propoints": 2
        },
        {
            "money": 500,
            "name": "Jamie Parke",
            "propoints": 2
        },
        {
            "money": 500,
            "name": "Gabe Walls",
            "propoints": 2
        },
        {
            "money": 500,
            "name": "Raymond Tautic",
            "propoints": 2
        },
        {
            "money": 500,
            "name": "Mark Herberholz",
            "propoints": 2
        },
        {
            "money": 500,
            "name": "Benjamin Peebles-Mundy",
            "propoints": 2
        },
        {
            "money": 500,
            "name": "Frank Karsten",
            "propoints": 2
        },
        {
            "money": 500,
            "name": "Brad Taulbee",
            "propoints": 2
        },
        {
            "money": 250,
            "name": "Gerard Fabiano",
            "propoints": 1
        },
        {
            "money": 250,
            "name": "Michael Hayner",
            "propoints": 1
        },
        {
            "money": 250,
            "name": "Phillip Napoli",
            "propoints": 1
        },
        {
            "money": 250,
            "name": "Zack Hall",
            "propoints": 1
        },
        {
            "money": 250,
            "name": "Victor King",
            "propoints": 1
        },
        {
            "money": 250,
            "name": "John Moore",
            "propoints": 1
        },
        {
            "money": 250,
            "name": "Don Smith",
            "propoints": 1
        },
        {
            "money": 250,
            "name": "Jim Ferraiolo",
            "propoints": 1
        },
        {
            "money": 250,
            "name": "Jeffrey Meyerson",
            "propoints": 1
        },
        {
            "money": 250,
            "name": "Kyle Smith",
            "propoints": 1
        },
        {
            "money": 250,
            "name": "Doug Hidlay",
            "propoints": 1
        },
        {
            "money": 250,
            "name": "Andrew Chapman",
            "propoints": 1
        },
        {
            "money": 250,
            "name": "Kenji Tsumura",
            "propoints": 1
        },
        {
            "money": 250,
            "name": "Shuhei Nakamura",
            "propoints": 1
        },
        {
            "money": 250,
            "name": "Morgan Douglass",
            "propoints": 1
        },
        {
            "money": 250,
            "name": "Paul Calder",
            "propoints": 1
        }
    ],
    "teamsize": 1
    
}
