{
    "type": "Grand Prix",
    "coverage": "https://magic.wizards.com/en/events/coverage/gpsen10",
    "date": "June 5-6, 2010",
    "season": "2010",
    "formats": [
        "Standard"
    ],
    "medium": "Tabletop",
    "id": "grand-prix-sendai-2010",
    "location": "Sendai, Japan",
    "logo": "gplogo.png",
    "name": "Grand Prix Sendai 2010",
    "standings": [
        {
            "money": 3500,
            "name": "Brian Kibler",
            "propoints": 10
        },
        {
            "money": 2300,
            "name": "Makihito Mihara",
            "propoints": 8
        },
        {
            "money": 1500,
            "name": "Shota Yasooka",
            "propoints": 6
        },
        {
            "money": 1500,
            "name": "Motoaki Itou",
            "propoints": 6
        },
        {
            "money": 1000,
            "name": "Takeshi Ozawa",
            "propoints": 5
        },
        {
            "money": 1000,
            "name": "Yuuya Watanabe",
            "propoints": 5
        },
        {
            "money": 1000,
            "name": "Hiroyuki Shimoya",
            "propoints": 5
        },
        {
            "money": 1000,
            "name": "Ryou Tasaki",
            "propoints": 5
        },
        {
            "money": 600,
            "name": "Yuutarou Hirashima",
            "propoints": 4
        },
        {
            "money": 600,
            "name": "Tatsuya Arakawa",
            "propoints": 4
        },
        {
            "money": 600,
            "name": "Yuuki Hirose",
            "propoints": 4
        },
        {
            "money": 600,
            "name": "Shuji Ueda",
            "propoints": 4
        },
        {
            "money": 500,
            "name": "Yuu Hashimoto",
            "propoints": 3
        },
        {
            "money": 500,
            "name": "Takatoshi Nakamura",
            "propoints": 3
        },
        {
            "money": 500,
            "name": "Jun'ichi Yabuta",
            "propoints": 3
        },
        {
            "money": 500,
            "name": "Tomoharu Saito",
            "propoints": 3
        },
        {
            "money": 400,
            "name": "Hayato Tashiro",
            "propoints": 2
        },
        {
            "money": 400,
            "name": "Haruki Nakatani",
            "propoints": 2
        },
        {
            "money": 400,
            "name": "Masaya Kitayama",
            "propoints": 2
        },
        {
            "money": 400,
            "name": "Junpei Oonishi",
            "propoints": 2
        },
        {
            "money": 400,
            "name": "Osamu Fujita",
            "propoints": 2
        },
        {
            "money": 400,
            "name": "Shintaro Ishimura",
            "propoints": 2
        },
        {
            "money": 400,
            "name": "Masaki Ushijima",
            "propoints": 2
        },
        {
            "money": 400,
            "name": "Yoshinori Ueki",
            "propoints": 2
        },
        {
            "money": 400,
            "name": "Yuuki Tsuba",
            "propoints": 2
        },
        {
            "money": 400,
            "name": "Yuki Matsumoto",
            "propoints": 2
        },
        {
            "money": 400,
            "name": "Ryoichi Tamada",
            "propoints": 2
        },
        {
            "money": 400,
            "name": "Yuki Uchida",
            "propoints": 2
        },
        {
            "money": 400,
            "name": "Koutarou Ootsuka",
            "propoints": 2
        },
        {
            "money": 400,
            "name": "Jun Igarashi",
            "propoints": 2
        },
        {
            "money": 400,
            "name": "Alex Lin",
            "propoints": 2
        },
        {
            "money": 400,
            "name": "Makoto Miyauchi",
            "propoints": 2
        },
        {
            "money": 200,
            "name": "Kou Kikutani",
            "propoints": 1
        },
        {
            "money": 200,
            "name": "Taiki Sakurai",
            "propoints": 1
        },
        {
            "money": 200,
            "name": "Takahiro Kaminaka",
            "propoints": 1
        },
        {
            "money": 200,
            "name": "Shiou Obata",
            "propoints": 1
        },
        {
            "money": 200,
            "name": "Tsuyoshi Ikeda",
            "propoints": 1
        },
        {
            "money": 200,
            "name": "Akio Chiba",
            "propoints": 1
        },
        {
            "money": 200,
            "name": "Kouji Takanashi",
            "propoints": 1
        },
        {
            "money": 200,
            "name": "Katsuhiro Mori",
            "propoints": 1
        },
        {
            "money": 200,
            "name": "Takuto Kimura",
            "propoints": 1
        },
        {
            "money": 200,
            "name": "Noriyuki Hagiwara",
            "propoints": 1
        },
        {
            "money": 200,
            "name": "Kousei Konno",
            "propoints": 1
        },
        {
            "money": 200,
            "name": "Shun Yamazaki",
            "propoints": 1
        },
        {
            "money": 200,
            "name": "Yuuya Hashizume",
            "propoints": 1
        },
        {
            "money": 200,
            "name": "Matteo Orsini-Jones",
            "propoints": 1
        },
        {
            "money": 200,
            "name": "Yuuma Okamoto",
            "propoints": 1
        },
        {
            "money": 200,
            "name": "Shuhei Nakamura",
            "propoints": 1
        },
        {
            "money": 200,
            "name": "Ryouta Takasugi",
            "propoints": 1
        },
        {
            "money": 200,
            "name": "Hiroshi Kawakami",
            "propoints": 1
        },
        {
            "money": 200,
            "name": "Kazuaki Kimura",
            "propoints": 1
        },
        {
            "money": 200,
            "name": "Tzu Ching Kuo",
            "propoints": 1
        },
        {
            "money": 200,
            "name": "Shunsuke Aka",
            "propoints": 1
        },
        {
            "money": 200,
            "name": "Ben Stark",
            "propoints": 1
        },
        {
            "money": 200,
            "name": "Yuusuke Endou",
            "propoints": 1
        },
        {
            "money": 200,
            "name": "Satoshi Komatsu",
            "propoints": 1
        },
        {
            "money": 200,
            "name": "Jun'ichi Honda",
            "propoints": 1
        },
        {
            "money": 200,
            "name": "Yuuki Kasahara",
            "propoints": 1
        },
        {
            "money": 200,
            "name": "Takafumi Matumoto",
            "propoints": 1
        },
        {
            "money": 200,
            "name": "Ryousuke Masuno",
            "propoints": 1
        },
        {
            "money": 200,
            "name": "Keiichi Chijimi",
            "propoints": 1
        },
        {
            "money": 200,
            "name": "Kazuto Hoshi",
            "propoints": 1
        },
        {
            "money": 200,
            "name": "Brett Blackman",
            "propoints": 1
        },
        {
            "money": 200,
            "name": "Yasushi Yamada",
            "propoints": 1
        }
    ],
    "teamsize": 1
    
}
