{
    "type": "Nationals - United Kingdom",
    "coverage": "https://groups.google.com/forum/#!searchin/rec.games.trading-cards.magic.misc/wotc$20release|sort:date/rec.games.trading-cards.magic.misc/X9sEZ1By14c/C3YWNN34guAJ",
    "date": "June 22, 1996",
    "formats": [
        "Standard"
    ],
    "medium": "Tabletop",
    "id": "nationals-united-kingdom-1996",
    "location": "Birmingham, United Kingdom",
    "logo": "nationals",
    "name": "Nationals United Kingdom 1996",
    "standings": [
        {
            "name": "Rob Salmon",
            "nationality": "GBR"
        },
        {
            "name": "Oliver Schneider"
        },
        {
            "name": "Steven Lamb",
            "rank": "3-4"
        },
        {
            "name": "Rory Hessian",
            "rank": "3-4"
        },
        {
            "name": "Jason Nicoll",
            "rank": "5-8"
        },
        {
            "name": "Daniel Ranson",
            "rank": "5-8"
        },
        {
            "name": "Clint Oldridge",
            "rank": "5-8"
        },
        {
            "name": "Anthony Goh",
            "rank": "5-8"
        },
        {
            "name": "Timothy Reader",
            "rank": "9-16"
        },
        {
            "name": "Brook North",
            "rank": "9-16"
        },
        {
            "name": "Mark Pui",
            "rank": "9-16"
        },
        {
            "name": "Dan Holden",
            "rank": "9-16"
        },
        {
            "name": "Jamie Badman",
            "rank": "9-16"
        },
        {
            "name": "Ivan Hanley",
            "rank": "9-16"
        },
        {
            "name": "Gary Campbell",
            "rank": "9-16"
        },
        {
            "name": "Paul Barclay",
            "rank": "9-16"
        },
        {
            "name": "Bertrand Lestree",
            "rank": "17"
        },
        {
            "name": "Uwe Stroinski",
            "rank": "Attended",
            "report": "https://web.archive.org/web/19990209025240/http://thedojo.net/tourney96/Uwe_1.txt"
        }

    ],
    "teamsize": 1
}