{
    "type": "Nationals - Hungary",
    "date": "January 1-August 31, 1997",
    "formats": [
        "Standard",
        "? Limited"
    ],
    "medium": "Tabletop",
    "id": "nationals-hungary-1997",
    "location": "Budapest, Hungary",
    "logo": "nationals",
    "name": "Nationals Hungary 1997",
    "standings": [
        {
            "name": "Miklos Tihor"
        },
        {
            "name": "Gabor Nagy"
        },
        {
            "name": "György Szalay"
        },
        {
            "name": "Gabor Papp"
        },
        {
            "name": "Attila Würth"
        },
        {
            "name": "Marcell Kardos"
        },
        {
            "name": "Tamas Hazai"
        },
        {
            "name": "Tamas Meszes"
        }
    ],
    "teamsize": 1
}