{
    "type": "Nationals - Slovenia",
    "coverage": "https://web.archive.org/web/20010213210312/http://www.wizards.com/international/europe/nationals.results.slovenia.asp",
    "date": "June 5-6, 1999",
    "season": "1998-99",
    "formats": [
        "Standard",
        "Rochester Draft"
    ],
    "medium": "Tabletop",
    "id": "nationals-slovenia-1999",
    "location": "Ljubljana, Slovenia",
    "logo": "nationals",
    "name": "Nationals Slovenia 1999",
    "standings": [
        {
            "name": "Ziga Skrbec"
        },
        {
            "name": "Andrej Brglez"
        },
        {
            "name": "Gregor Strubelj"
        },
        {
            "name": "Ziga Fritz"
        },
        {
            "name": "Andrej Podgorsek"
        },
        {
            "name": "Andrej Renko"
        },
        {
            "name": "Saso Milac"
        },
        {
            "name": "Andrej Cibej"
        }
    ],
    "teamsize": 1
}