{
    "type": "Nationals - Turkey",
    "date": "May 3-4, 2003",
    "season": "2002-03",
    "formats": [
        "Standard",
        "Rochester Draft"
    ],
    "medium": "Tabletop",
    "id": "nationals-turkey-2003",
    "location": "Istanbul, Turkey",
    "logo": "nationals",
    "name": "Nationals Turkey 2003",
    "standings": [
        {
            "name": "Eda Bilsel"
        },
        {
            "name": "Alp Ovutmen"
        },
        {
            "name": "Siyar Erzen"
        },
        {
            "name": "Eray Veral"
        },
        {
            "name": "Onur Konuralp"
        },
        {
            "name": "Sarp Ovutmen"
        },
        {
            "name": "Gokhan Habiboglu"
        },
        {
            "name": "Genco Gun"
        }
    ],
    "teamsize": 1
}