{
    "type": "Nationals - Latvia",
    "date": "August 18-19, 2018",
    "season": "2017-18",
    "formats": [
        "Standard",
        "Booster Draft"
    ],
    "medium": "Tabletop",
    "id": "nationals-latvia-2018",
    "location": "Riga, Latvia",
    "logo": "nationals-18",
    "name": "Nationals Latvia 2018",
    "standings": [
        {
            "name": "Gints Dreimanis",
            "propoints": 3
        },
        {
            "name": "Viktors Kazanskis",
            "propoints": 3
        },
        {
            "name": "Kirils Obuks",
            "propoints": 1
        },
        {
            "name": "Sergej Plotnikov",
            "propoints": 1
        },
        {
            "name": "Andrew Potashev"
        },
        {
            "name": "Jonn Mostovoy"
        },
        {
            "name": "Oskars Zandersons"
        },
        {
            "name": "Pauls Verners"
        }
    ],
    "teamsize": 1
}