{
    "type": "Nationals - Hungary",
    "date": "January 1-September 8, 2004",
    "formats": [
        "Standard",
        "Booster Draft"
    ],
    "medium": "Tabletop",
    "id": "nationals-hungary-2004",
    "location": "Budapest, Hungary",
    "logo": "nationals",
    "name": "Nationals Hungary 2004",
    "standings": [
        {
            "name": "Karoly Liptak"
        },
        {
            "name": "Andras Balogh"
        },
        {
            "name": "Gabor Papp"
        },
        {
            "name": "Gabor Kocsis"
        },
        {
            "name": "Ervin Hosszu"
        },
        {
            "name": "Tamas Kornis"
        },
        {
            "name": "Zsolt Tököli"
        },
        {
            "name": "Gergely Gardos"
        }
    ],
    "teamsize": 1
}