{
    "type": "Regional Championship",
    "coverage": "https://magic.gg/events/anz-super-series-finals-sydney",
    "date": "November 26-27, 2022",
    "season": "2022-23",
    "formats": [
        "Pioneer"
    ],
    "medium": "Tabletop",
    "id": "regional-championship-sydney-2022",
    "location": "Sydney, Australia",
    "logo": "mtg-yellow",
    "name": "ANZ Super Series Finals: Sydney",
    "standings": [
        {
            "money": 5000,
            "name": "Anthony Lee",
            "matchpoints": 19
        },
        {
            "money": 2500,
            "name": "David Mines",
            "matchpoints": 19
        },
        {
            "money": 1250,
            "name": "Steven Hitchcock",
            "matchpoints": 22
        },
        {
            "money": 1250,
            "name": "Nicholas Malcolm Preston",
            "matchpoints": 20
        },
        {
            "money": 750,
            "name": "Brennan Crawford",
            "matchpoints": 19
        },
        {
            "money": 750,
            "name": "Chris Miller",
            "matchpoints": 19
        },
        {
            "money": 750,
            "name": "Daniel Bretherton",
            "matchpoints": 19
        },
        {
            "money": 750,
            "name": "Daniel Riley",
            "matchpoints": 19
        },
        {
            "money": 250,
            "name": "Michael Russell",
            "matchpoints": 18
        },
        {
            "money": 250,
            "name": "Jingwei Zheng",
            "matchpoints": 18
        },
        {
            "money": 250,
            "name": "Brandon Rashad",
            "matchpoints": 18
        },
        {
            "money": 250,
            "name": "Chris Cousens",
            "matchpoints": 18
        },
        {
            "money": 250,
            "name": "Matthew Anderson",
            "matchpoints": 18
        },
        {
            "money": 250,
            "name": "Nicholas Turner",
            "matchpoints": 18
        },
        {
            "money": 250,
            "name": "Calum Gittins",
            "matchpoints": 18
        },
        {
            "money": 250,
            "name": "Callum Howes",
            "matchpoints": 18
        }
    ],
    "teamsize": 1
    
}