{
    "type": "Regional Championship",
    "coverage": "https://magic.gg/events/south-america-magic-series-santiago-2023-r3",
    "date": "July 1-2, 2023",
    "season": "2022-23",
    "formats": [
        "Pioneer"
    ],
    "medium": "Tabletop",
    "id": "regional-championship-santiago-2-2023",
    "location": "Santiago de Chile, Chile",
    "logo": "mtg-yellow",
    "name": "South America Magic Series: Santiago",
    "standings": [
{
"name": "Martin Dominguez",
"matchpoints": 18,
"money": 4000
},
{
"name": "Matias Leveratto",
"matchpoints": 16,
"money": 2000
},
{
"name": "Freddy Paredes",
"matchpoints": 18,
"money": 1200
},
{
"name": "Agustin Colombo",
"matchpoints": 17,
"money": 1200
},
{
"name": "Luis Salvatto",
"matchpoints": 19,
"money": 750
},
{
"name": "Boris Marin",
"matchpoints": 17,
"money": 750
},
{
"name": "Juan Corrales",
"matchpoints": 17,
"money": 750
},
{
"name": "Mauro Capello",
"matchpoints": 16,
"money": 750
},
{
"name": "Diego Olfos Vargas",
"matchpoints": 16,
"money": 250
},
{
"name": "Renzo Arana",
"matchpoints": 15,
"money": 250
},
{
"name": "Sebastian Antonio Toledo Diaz",
"matchpoints": 15,
"money": 250
},
{
"name": "Luis Gutiérrez",
"matchpoints": 15,
"money": 250
},
{
"name": "Ivan Morala",
"matchpoints": 15,
"money": 250
},
{
"name": "Martin Del Güercio",
"matchpoints": 15,
"money": 250
},
{
"name": "José Ignacio Fernández Rico",
"matchpoints": 15,
"money": 250
},
{
"name": "Sebastian Pozzo",
"matchpoints": 15,
"money": 250
},
{
"name": "Cristopher Maturana",
"matchpoints": 15,
"money": 100
},
{
"name": "Daniel Fernandez (CHL)",
"matchpoints": 15,
"money": 100
},
{
"name": "Marcelo López Lagos",
"matchpoints": 15,
"money": 100
},
{
"name": "Gustavo Nicolas Gabriel",
"matchpoints": 15,
"money": 100
},
{
"name": "Gonzalo Vera",
"matchpoints": 13,
"money": 100
},
{
"name": "Guillermo Sulimovich",
"matchpoints": 13,
"money": 100
},
{
"name": "Freddy Valdivieso",
"matchpoints": 13,
"money": 100
},
{
"name": "Sergio Campos",
"matchpoints": 13,
"money": 100
},
{
"name": "Leandro Peralta",
"matchpoints": 13,
"money": 100
},
{
"name": "Rodrigo Gayoso",
"matchpoints": 13,
"money": 100
},
{
"name": "Joaquín Madariaga",
"matchpoints": 13,
"money": 100
},
{
"name": "Felipe Millán",
"matchpoints": 13,
"money": 100
},
{
"name": "Andres Bozzo",
"matchpoints": 13,
"money": 100
},
{
"name": "Juan Martin Baccino",
"matchpoints": 13,
"money": 100
},
{
"name": "Francisco Vega",
"matchpoints": 12,
"money": 100
},
{
"name": "Julian Prado",
"matchpoints": 12,
"money": 100
},
{
"name": "Guillermo Joel Bruna",
"matchpoints": 12
},
{
"name": "Javier Núñez",
"matchpoints": 12
},
{
"name": "Julio Fernández",
"matchpoints": 12
},
{
"name": "Víctor Delgado",
"matchpoints": 12
},
{
"name": "Sebastian Mora",
"matchpoints": 12
},
{
"name": "Francisco Gonzalez Iturriaga",
"matchpoints": 12
},
{
"name": "Carlos Vargas",
"matchpoints": 12
},
{
"name": "Ivan Concha",
"matchpoints": 12
},
{
"name": "Diego Hurtado Sánchez",
"matchpoints": 12
},
{
"name": "Francisca Garcia",
"matchpoints": 12
},
{
"name": "Alvarez Alejo",
"matchpoints": 12
},
{
"name": "Carlos Suárez",
"matchpoints": 12
},
{
"name": "Sebastián Montalbán",
"matchpoints": 12
},
{
"name": "Kabir Qayoumi Martinez",
"matchpoints": 11
},
{
"name": "Andrés Espinosa",
"matchpoints": 10
},
{
"name": "Pablo Vergara",
"matchpoints": 10
},
{
"name": "Juan Paulo Ramirez",
"matchpoints": 10
},
{
"name": "Daniel Vargas",
"matchpoints": 10
},
{
"name": "Diego Galaz",
"matchpoints": 10
},
{
"name": "Marco Bahamonde",
"matchpoints": 10
},
{
"name": "Carlos Medina",
"matchpoints": 10
},
{
"name": "Felipe Ignacio Angel Cortes",
"matchpoints": 10
},
{
"name": "Mauricio Flores",
"matchpoints": 9
},
{
"name": "Maximiliano Daruich",
"matchpoints": 9
},
{
"name": "Pradenas Ernesto",
"matchpoints": 9
},
{
"name": "Benjamin Rojas",
"matchpoints": 9
},
{
"name": "Camilo Niño",
"matchpoints": 9
},
{
"name": "Jimmy Sam",
"matchpoints": 9
},
{
"name": "Mario Muñoz",
"matchpoints": 9
},
{
"name": "Luis Ardiles",
"matchpoints": 9
},
{
"name": "Sabrina Hochman",
"matchpoints": 9
},
{
"name": "Adrian Canepa Casabo",
"matchpoints": 9
},
{
"name": "Rodrigo Lopez",
"matchpoints": 9
},
{
"name": "Eduardo Torres",
"matchpoints": 9
},
{
"name": "Federico Giardini",
"matchpoints": 7
},
{
"name": "Jorge Vargas",
"matchpoints": 7
},
{
"name": "Gian Luca Bozzo",
"matchpoints": 7
},
{
"name": "Luis Allende",
"matchpoints": 7
},
{
"name": "Marco Gaete",
"matchpoints": 7
},
{
"name": "Ernesto Sosa",
"matchpoints": 7
},
{
"name": "Michael Parraga",
"matchpoints": 7
},
{
"name": "Nicolas Morales",
"matchpoints": 6
},
{
"name": "Nicolas Velasquez",
"matchpoints": 6
},
{
"name": "Cristian Chong",
"matchpoints": 6
},
{
"name": "Luis Gallardo",
"matchpoints": 6
},
{
"name": "Mauro Acerenza",
"matchpoints": 6
},
{
"name": "Pedro De Diego",
"matchpoints": 6
},
{
"name": "Ricardo Cortes",
"matchpoints": 6
},
{
"name": "Leonardo Canalejo",
"matchpoints": 6
},
{
"name": "Antonio Mancilla",
"matchpoints": 6
},
{
"name": "Camilo Fernandez",
"matchpoints": 6
},
{
"name": "Marcos Paredes",
"matchpoints": 6
},
{
"name": "Rodolfo Ocampo",
"matchpoints": 6
},
{
"name": "Carlos Morales",
"matchpoints": 6
},
{
"name": "Pancho A. Miranda",
"matchpoints": 6
},
{
"name": "Guillermo Munoz Tejo",
"matchpoints": 4
},
{
"name": "Emiliano Trepichio",
"matchpoints": 4
},
{
"name": "Paula Oyarzun",
"matchpoints": 4
},
{
"name": "Javier Flores",
"matchpoints": 4
},
{
"name": "Jose Salini",
"matchpoints": 3
},
{
"name": "Andrés Camargo",
"matchpoints": 3
},
{
"name": "José Carrasco",
"matchpoints": 3
},
{
"name": "Santiago Bigatti",
"matchpoints": 3
},
{
"name": "Alfredo de Jorge",
"matchpoints": 3
},
{
"name": "Felipe Gonzalez",
"matchpoints": 3
},
{
"name": "Pedro Gonzalez",
"matchpoints": 3
},
{
"name": "Facundo Conde",
"matchpoints": 3
},
{
"name": "Carlos Mohor",
"matchpoints": 3
},
{
"name": "Esteban Muñoz",
"matchpoints": 3
},
{
"name": "Paulo Escalante",
"matchpoints": 3
},
{
"name": "Pablo Valenzuela",
"matchpoints": 1
},
{
"name": "Rolando Flores Pauletti",
"matchpoints": 1
},
{
"name": "Daniel Soto",
"matchpoints": 1
},
{
"name": "Federico Arguissein",
"matchpoints": 1
},
{
"name": "Rodolfo Delgado",
"matchpoints": 1
},
{
"name": "José Toledo",
"matchpoints": 0
},
{
"name": "Cristián Valdés",
"matchpoints": 0
},
{
"name": "Tomas Donofrio",
"matchpoints": 0
},
{
"name": "Patricio Barria",
"matchpoints": 0
},
{
"name": "Antón Nava Ivanov",
"matchpoints": 0
},
{
"name": "Fernando Yaksic Carrasco",
"matchpoints": 0
},
{
"name": "Darwin Fuenzalida",
"matchpoints": 0
},
{
"name": "Emiliano Passoni",
"matchpoints": 0
}


    ],
    "teamsize": 1
    
}